epicsdbbuilder/__init__.py
epicsdbbuilder/_version_git.py
epicsdbbuilder/bits.py
epicsdbbuilder/const_array.py
epicsdbbuilder/dbd.py
epicsdbbuilder/fanout.py
epicsdbbuilder/mydbstatic.py
epicsdbbuilder/parameter.py
epicsdbbuilder/recordbase.py
epicsdbbuilder/recordnames.py
epicsdbbuilder/recordset.py
epicsdbbuilder-1.5.dist-info/LICENSE
epicsdbbuilder-1.5.dist-info/METADATA
epicsdbbuilder-1.5.dist-info/WHEEL
epicsdbbuilder-1.5.dist-info/top_level.txt
epicsdbbuilder-1.5.dist-info/RECORD
