Metadata-Version: 2.1
Name: epicsdbbuilder
Version: 1.5
Summary: EPICS Database Builder
Home-page: https://github.com/dls-controls/epicsdbbuilder
Author: Michael Abbott
Author-email: Michael.Abbott@diamond.ac.uk
License: Apache License 2.0
Platform: UNKNOWN
Classifier: Development Status :: 5 - Production/Stable
Classifier: License :: OSI Approved :: Apache Software License
Classifier: Programming Language :: Python :: 2.7
Classifier: Programming Language :: Python :: 3.6
Classifier: Programming Language :: Python :: 3.7
Classifier: Programming Language :: Python :: 3.8
